AUTHORS.rst
HISTORY.rst
LICENSE
MANIFEST.in
README.rst
requirements.txt
setup.py
setup_requirements.txt
test_requirements.txt
atlasclient/__init__.py
atlasclient/base.py
atlasclient/client.py
atlasclient/events.py
atlasclient/exceptions.py
atlasclient/models.py
atlasclient/utils.py
atlasclient.egg-info/PKG-INFO
atlasclient.egg-info/SOURCES.txt
atlasclient.egg-info/dependency_links.txt
atlasclient.egg-info/not-zip-safe
atlasclient.egg-info/requires.txt
atlasclient.egg-info/top_level.txt
docs/Makefile
docs/authors.rst
docs/conf.py
docs/contributing.rst
docs/history.rst
docs/index.rst
docs/installation.rst
docs/make.bat
docs/readme.rst
docs/usage.rst
docs/utils.rst
tests/__init__.py
tests/conftest.py
tests/test_base.py
tests/test_client.py
tests/test_models.py
tests/test_utils.py
tests/query_json/entity_post.json
tests/query_json/entityguid_classifications_post.json
tests/response_json/.entityguid_get.json.swo
tests/response_json/admin_metrics.json
tests/response_json/entity_post.json
tests/response_json/entitybulk_get.json
tests/response_json/entitybulkclassification_post.json
tests/response_json/entityguid_classification_get.json
tests/response_json/entityguid_delete.json
tests/response_json/entityguid_get.json
tests/response_json/lineage_guid_get.json
tests/response_json/relationship_guid_get.json
tests/response_json/relationshipdef_guid_get.json
tests/response_json/search_attribute_get.json
tests/response_json/search_saved_get.json
tests/response_json/search_saved_guid_get.json
tests/response_json/search_saved_name_get.json
tests/response_json/search_saved_update.json
tests/response_json/typedefs_get.json
tests/response_json/typedefs_headers_get.json