Metadata-Version: 1.1
Name: atlasclient
Version: 1.0.0
Summary: Apache Atlas client
Home-page: https://github.com/jpoullet2000/atlasclient
Author: Jean-Baptiste Poullet
Author-email: jeanbaptistepoullet@gmail.com
License: Apache Software License 2.0
Keywords: atlasclient
Platform: UNKNOWN
Classifier: Development Status :: 2 - Pre-Alpha
Classifier: Intended Audience :: Developers
Classifier: License :: OSI Approved :: Apache Software License
Classifier: Natural Language :: English
Classifier: Programming Language :: Python :: 2
Classifier: Programming Language :: Python :: 2.7
Classifier: Programming Language :: Python :: 3
Classifier: Programming Language :: Python :: 3.5
Classifier: Programming Language :: Python :: 3.6
